apytypes/__init__.py
apytypes/_apytypes.cpython-313-aarch64-linux-musl.so
apytypes/_apytypes.pyi
apytypes/_array_functions.py
apytypes/_typing.py
apytypes/_utils.py
apytypes/_version.py
apytypes/py.typed
apytypes/vhdl.py
apytypes.libs/libgcc_s-2d945d6c.so.1
apytypes.libs/libstdc++-85f2cd6d.so.6.0.33
apytypes-0.4.0.dist-info/METADATA
apytypes-0.4.0.dist-info/WHEEL
apytypes-0.4.0.dist-info/RECORD
