Metadata-Version: 2.1
Name: apytypes
Version: 0.4.0
Summary: Python package for custom fixed-point and floating-point formats
Keywords: fixed-point,floating-point,finite word length
Author-Email: Oscar Gustafsson <oscar.gustafsson@gmail.com>, Mikael Henriksson <mikael.henriksson@liu.se>, Theodor Lindberg <theodor.lindberg@liu.se>
Classifier: Development Status :: 3 - Alpha
Classifier: Intended Audience :: Science/Research
Classifier: License :: OSI Approved :: MIT License
Classifier: Operating System :: OS Independent
Classifier: Programming Language :: Python :: 3
Classifier: Programming Language :: Python :: 3.10
Classifier: Programming Language :: Python :: 3.11
Classifier: Programming Language :: Python :: 3.12
Classifier: Programming Language :: Python :: 3.13
Classifier: Topic :: Scientific/Engineering :: Electronic Design Automation (EDA)
Project-URL: Repository, https://github.com/apytypes/apytypes/
Project-URL: Issues, https://github.com/apytypes/apytypes/issues
Project-URL: Homepage, https://apytypes.github.io/
Project-URL: Documentation, https://apytypes.github.io/apytypes/
Project-URL: Changelog, https://github.com/apytypes/apytypes/blob/main/CHANGELOG.md
Requires-Python: >=3.10
Provides-Extra: docs
Requires-Dist: breathe>=4.35; extra == "docs"
Requires-Dist: furo>=2024; extra == "docs"
Requires-Dist: matplotlib>=3.7; extra == "docs"
Requires-Dist: numpydoc>=1.7; extra == "docs"
Requires-Dist: setuptools>=70; extra == "docs"
Requires-Dist: sphinx>=7; extra == "docs"
Requires-Dist: sphinx_copybutton>=0.5; extra == "docs"
Requires-Dist: sphinx_gallery>=0.16; extra == "docs"
Requires-Dist: m2r2; extra == "docs"
Requires-Dist: docutils; extra == "docs"
Requires-Dist: numpy>=1.25; extra == "docs"
Requires-Dist: scipy; extra == "docs"
Requires-Dist: cocotb>=1.9.1; extra == "docs"
Provides-Extra: test
Requires-Dist: numpy>=1.25; extra == "test"
Requires-Dist: pytest>=8.2; extra == "test"
Provides-Extra: test-hdl
Requires-Dist: numpy>=1.25; extra == "test-hdl"
Requires-Dist: pytest>=8.2; extra == "test-hdl"
Requires-Dist: cocotb>=1.9.1; extra == "test-hdl"
Requires-Dist: vunit-hdl; extra == "test-hdl"
Provides-Extra: dev
Requires-Dist: nanobind>=2.8.0; extra == "dev"
Provides-Extra: benchmark
Requires-Dist: numpy>=1.25; extra == "benchmark"
Requires-Dist: pytest>=8.2; extra == "benchmark"
Requires-Dist: pytest-benchmark; extra == "benchmark"
Provides-Extra: comparison
Requires-Dist: fpbinary; extra == "comparison"
Requires-Dist: fixedpoint; extra == "comparison"
Requires-Dist: fxpmath>=0.4.9; extra == "comparison"
Requires-Dist: spfpm; extra == "comparison"
Requires-Dist: numfi>=0.5; extra == "comparison"
Requires-Dist: numpy>=1.25; extra == "comparison"
Requires-Dist: matplotlib>=3.7; extra == "comparison"
